AsteriskCommand/__init__.py
AsteriskCommand/atxfer.py
AsteriskCommand/clear_idle_call_actors.py
AsteriskCommand/core_show_channels.py
AsteriskCommand/get_agent_status.py
AsteriskCommand/get_info_anexos.py
AsteriskCommand/hangup.py
AsteriskCommand/originate.py
AsteriskCommand/queue_add.py
AsteriskCommand/queue_pause.py
AsteriskCommand/queue_remove.py
AsteriskCommand/queue_status.py
AsteriskCommand/queues.py
AsteriskCommand/redirect.py
AsteriskCommand/set_var.py
AsteriskCommand/sip_peers.py
AsteriskCommand/sip_peers_status.py
AsteriskCommand/commons/__init__.py
AsteriskCommand/commons/asterisk_action.py
AsteriskCommand/commons/asterisk_command.py
tests/__init__.py
tests/test_receive_commands.py
tests/commands/__init__.py
tests/commands/auxiliar_commands.py
tests/commands/test_atxfer_command.py
tests/commands/test_clear_idle_call_actors_command.py
tests/commands/test_core_show_channels_command.py
tests/commands/test_get_agent_status_command.py
tests/commands/test_get_info_anexos_command.py
tests/commands/test_hangup_command.py
tests/commands/test_originate_command.py
tests/commands/test_queue_add_command.py
tests/commands/test_queue_pause_command.py
tests/commands/test_queue_remove_command.py
tests/commands/test_queue_status_command.py
tests/commands/test_queues_command.py
tests/commands/test_redirect_command.py
tests/commands/test_set_var_command.py
tests/commands/test_sip_peers_command.py
tests/commands/test_sip_peers_status_command.py
asteriskcommands-1.0.1.dist-info/METADATA
asteriskcommands-1.0.1.dist-info/WHEEL
asteriskcommands-1.0.1.dist-info/top_level.txt
asteriskcommands-1.0.1.dist-info/RECORD
