Metadata-Version: 2.1
Name: asteriskcommands
Version: 1.0.1
Summary: API for share asterisk commands beetween the microservices
Home-page: UNKNOWN
Author: Juares Vermelho Diaz (CL3k)
Author-email: jvermelho@cl3k.com
License: UNKNOWN
Keywords: Asterisk commands
Platform: UNKNOWN
